ouqu_tp/__init__.py
ouqu_tp/__main__.py
ouqu_tp/cli/__init__.py
ouqu_tp/cli/ideal.py
ouqu_tp/cli/main.py
ouqu_tp/cli/noisy.py
ouqu_tp/cli/noisyevo.py
ouqu_tp/cli/trance.py
ouqu_tp/internal/QASMtoqulacs.py
ouqu_tp/internal/__init__.py
ouqu_tp/internal/auto_noise.py
ouqu_tp/internal/debug.py
ouqu_tp/internal/getval.py
ouqu_tp/internal/make_Cnet.py
ouqu_tp/internal/ot_io.py
ouqu_tp/internal/qelib1.inc
ouqu_tp/internal/sampleval.py
ouqu_tp/internal/shot_obs.py
ouqu_tp/internal/simulate.py
ouqu_tp/internal/tran.py
ouqu_tp/internal/trancepile.py
ouqu_tp/kasika.py
ouqu_tp/kasikb.py
ouqu_tp/servicers/__init__.py
ouqu_tp/servicers/add.inc
ouqu_tp/servicers/config.py
ouqu_tp/servicers/default_device_topology_json.py
ouqu_tp/servicers/exec_ouqu.py
ouqu_tp/servicers/ouqu_tp.py
ouqu_tp-1.0.3.dist-info/LICENSE
ouqu_tp-1.0.3.dist-info/METADATA
ouqu_tp-1.0.3.dist-info/WHEEL
ouqu_tp-1.0.3.dist-info/entry_points.txt
ouqu_tp-1.0.3.dist-info/RECORD
