Metadata-Version: 2.3
Name: ouqu-tp
Version: 1.0.3
Summary: 
Author: Your Name
Author-email: you@example.com
Requires-Python: >=3.9,<4.0
Classifier: Programming Language :: Python :: 3
Classifier: Programming Language :: Python :: 3.9
Classifier: Programming Language :: Python :: 3.10
Classifier: Programming Language :: Python :: 3.11
Classifier: Programming Language :: Python :: 3.12
Classifier: Programming Language :: Python :: 3.13
Requires-Dist: numpy (>=1.21.2,<2.0.0)
Requires-Dist: parse (>=1.19.0,<2.0.0)
Requires-Dist: qulacs (>=0.5.0)
Requires-Dist: scipy (>=1.7.3,<2.0.0)
Requires-Dist: typer (>=0.4.0,<0.5.0)
Project-URL: Repository, https://github.com/Qulacs-Osaka/ouqu-tp
